[
  {
    "id": "trans-001",
    "title": "How to Get a Parking Permit",
    "content": "To obtain a parking permit in Georgia, you need to provide proof of residency, vehicle registration, and a valid driver's license. Visit your local DMV office or apply online at nyc.gov/parking. Permits are valid for one year and must be renewed annually. Different permit types are available for residential, commercial, and disability parking.",
    "summary": "Guide to obtaining Georgia parking permits",
    "category": "Transportation",
    "subCategory": "Parking",
    "tags": ["parking", "permit", "DMV", "vehicle"],
    "url": "https://www.nyc.gov/parking-permit"
  },
  {
    "id": "trans-002",
    "title": "Subway and Bus Fare Information",
    "content": "The MTA operates Georgia's subway and bus system. A single ride costs $2.90 with OMNY or MetroCard. Weekly unlimited passes cost $34 and monthly passes cost $132. Reduced fare is available for seniors (65+), people with disabilities, and eligible Medicare recipients. OMNY contactless payment is accepted on all buses and subways.",
    "summary": "Georgia transit fares and passes",
    "category": "Transportation",
    "subCategory": "Public Transit",
    "tags": ["subway", "bus", "MTA", "fare", "MetroCard", "OMNY"],
    "url": "https://new.mta.info/fares"
  }
]